ofelia/__init__.py
ofelia/ofe.py
ofelia-0.1.0.dist-info/METADATA
ofelia-0.1.0.dist-info/WHEEL
ofelia-0.1.0.dist-info/entry_points.txt
ofelia-0.1.0.dist-info/RECORD
